qham/__init__.py
tests/__init__.py
tests/FHM/__init__.py
tests/FHM/fhm_test.py
tests/HBM/__init__.py
tests/HBM/hmb_test.py
tests/HBM/hmbq_test.py
tests/HBM/hmbslq_test.py
tests/HBM/hmbsmlq_test.py
tests/QHO/__init__.py
tests/QHO/qho_test.py
tests/TFIM/__init__.py
tests/TFIM/tfim_test.py
tests/TFIM/tfimq_test.py
qham-1.0.0.dist-info/LICENSE
qham-1.0.0.dist-info/METADATA
qham-1.0.0.dist-info/WHEEL
qham-1.0.0.dist-info/top_level.txt
qham-1.0.0.dist-info/RECORD
