Metadata-Version: 2.1
Name: qham
Version: 1.0.0
Summary: A package for simulating quantum Hamiltonians.
Home-page: https://github.com/yourusername/yourpackagename
Author: Kaushik Chintam
Author-email: kaushikam12@gmail.com
Classifier: Development Status :: 3 - Alpha
Classifier: Intended Audience :: Developers
Classifier: Intended Audience :: Education
Classifier: Natural Language :: English
Classifier: Programming Language :: Python :: 3
Classifier: Programming Language :: Python :: 3.8
Classifier: Programming Language :: Python :: 3.9
Classifier: Programming Language :: Python :: 3.10
Requires-Python: >=3.6
License-File: LICENSE
Requires-Dist: numpy >=1.18.1
Requires-Dist: qiskit >=0.7.0
Requires-Dist: torch >=1.7.0
Requires-Dist: scipy >=1.4.1
Requires-Dist: matplotlib >=3.1.3
Requires-Dist: pytest >=5.3.5
